{"Players":[{"Player":"Kamil_J","TotalPoints":28,"Wins":2,"Cla":37,"Supplies":18,"PowerTokens":43,"MinutesPerMove":160.5693693693694,"Moves":111,"Houses":[{"Game":302029,"House":"Tyrell","IsWinner":false,"Points":4,"BattlePenalty":0,"Strongholds":2,"Castles":2,"Cla":9,"Supplies":2,"PowerTokens":8,"MinutesPerMove":169.8,"Moves":31,"Stats":{"Battles":{"Won":7,"Lost":2},"Kills":{"Footmen":2,"Knights":3,"SiegeEngines":1,"Ships":0},"Casualties":{"Footmen":0,"Knights":0,"SiegeEngines":0,"Ships":0},"PowerTokens":{"ConsolidatePower":5,"Raids":0,"GameOfThrones":6,"Wildlings":0,"Tywin":0},"Bids":{"IronThrone":1,"Fiefdoms":1,"KingsCourt":5,"Wildlings":0,"Aeron":0}}},{"Game":302027,"House":"Baratheon","IsWinner":true,"Points":7,"BattlePenalty":0,"Strongholds":2,"Castles":2,"Cla":6,"Supplies":4,"PowerTokens":1,"MinutesPerMove":155.3,"Moves":22,"Stats":{"Battles":{"Won":1,"Lost":0},"Kills":{"Footmen":0,"Knights":0,"SiegeEngines":0,"Ships":0},"Casualties":{"Footmen":0,"Knights":0,"SiegeEngines":0,"Ships":0},"PowerTokens":{"ConsolidatePower":8,"Raids":0,"GameOfThrones":0,"Wildlings":0,"Tywin":0},"Bids":{"IronThrone":0,"Fiefdoms":2,"KingsCourt":9,"Wildlings":0,"Aeron":0}}},{"Game":301873,"House":"Stark","IsWinner":false,"Points":4,"BattlePenalty":0,"Strongholds":1,"Castles":3,"Cla":5,"Supplies":1,"PowerTokens":19,"MinutesPerMove":166.2,"Moves":16,"Stats":{"Battles":{"Won":0,"Lost":0},"Kills":{"Footmen":0,"Knights":0,"SiegeEngines":0,"Ships":0},"Casualties":{"Footmen":0,"Knights":0,"SiegeEngines":0,"Ships":0},"PowerTokens":{"ConsolidatePower":6,"Raids":0,"GameOfThrones":9,"Wildlings":0,"Tywin":0},"Bids":{"IronThrone":0,"Fiefdoms":0,"KingsCourt":0,"Wildlings":1,"Aeron":0}}},{"Game":301874,"House":"Martell","IsWinner":true,"Points":7,"BattlePenalty":0,"Strongholds":1,"Castles":3,"Cla":7,"Supplies":2,"PowerTokens":2,"MinutesPerMove":117,"Moves":14,"Stats":{"Battles":{"Won":2,"Lost":0},"Kills":{"Footmen":0,"Knights":0,"SiegeEngines":0,"Ships":0},"Casualties":{"Footmen":0,"Knights":0,"SiegeEngines":0,"Ships":0},"PowerTokens":{"ConsolidatePower":1,"Raids":0,"GameOfThrones":3,"Wildlings":0,"Tywin":0},"Bids":{"IronThrone":0,"Fiefdoms":0,"KingsCourt":3,"Wildlings":1,"Aeron":0}}},{"Game":301923,"House":"Greyjoy","IsWinner":false,"Points":3,"BattlePenalty":0,"Strongholds":2,"Castles":1,"Cla":5,"Supplies":4,"PowerTokens":13,"MinutesPerMove":197.8,"Moves":12,"Stats":{"Battles":{"Won":1,"Lost":0},"Kills":{"Footmen":0,"Knights":0,"SiegeEngines":0,"Ships":0},"Casualties":{"Footmen":0,"Knights":0,"SiegeEngines":0,"Ships":0},"PowerTokens":{"ConsolidatePower":8,"Raids":0,"GameOfThrones":3,"Wildlings":0,"Tywin":0},"Bids":{"IronThrone":0,"Fiefdoms":0,"KingsCourt":0,"Wildlings":2,"Aeron":0}}},{"Game":301878,"House":"Lannister","IsWinner":false,"Points":3,"BattlePenalty":0,"Strongholds":2,"Castles":1,"Cla":5,"Supplies":5,"PowerTokens":0,"MinutesPerMove":154.5,"Moves":16,"Stats":{"Battles":{"Won":0,"Lost":0},"Kills":{"Footmen":0,"Knights":0,"SiegeEngines":0,"Ships":0},"Casualties":{"Footmen":0,"Knights":0,"SiegeEngines":0,"Ships":0},"PowerTokens":{"ConsolidatePower":3,"Raids":0,"GameOfThrones":0,"Wildlings":0,"Tywin":0},"Bids":{"IronThrone":3,"Fiefdoms":2,"KingsCourt":3,"Wildlings":0,"Aeron":0}}}],"PenaltiesPoints":0,"PenaltiesDetails":[],"Stats":{"Battles":{"Won":11,"Lost":2},"Kills":{"Footmen":2,"Knights":3,"SiegeEngines":1,"Ships":0},"Casualties":{"Footmen":0,"Knights":0,"SiegeEngines":0,"Ships":0},"PowerTokens":{"ConsolidatePower":31,"Raids":0,"GameOfThrones":21,"Wildlings":0,"Tywin":0},"Bids":{"IronThrone":4,"Fiefdoms":5,"KingsCourt":20,"Wildlings":4,"Aeron":0}},"IsPromoted":true,"IsRelegated":false,"Position":1},{"Player":"Lance","TotalPoints":25,"Wins":2,"Cla":27,"Supplies":17,"PowerTokens":28,"MinutesPerMove":336.92352941176466,"Moves":102,"Houses":[{"Game":302026,"House":"Stark","IsWinner":false,"Points":4,"BattlePenalty":0,"Strongholds":1,"Castles":3,"Cla":5,"Supplies":1,"PowerTokens":7,"MinutesPerMove":346.9,"Moves":17,"Stats":{"Battles":{"Won":1,"Lost":0},"Kills":{"Footmen":0,"Knights":0,"SiegeEngines":0,"Ships":0},"Casualties":{"Footmen":0,"Knights":0,"SiegeEngines":0,"Ships":0},"PowerTokens":{"ConsolidatePower":2,"Raids":0,"GameOfThrones":6,"Wildlings":0,"Tywin":0},"Bids":{"IronThrone":0,"Fiefdoms":0,"KingsCourt":5,"Wildlings":1,"Aeron":0}}},{"Game":301872,"House":"Baratheon","IsWinner":false,"Points":2,"BattlePenalty":0,"Strongholds":1,"Castles":1,"Cla":2,"Supplies":2,"PowerTokens":9,"MinutesPerMove":511.8,"Moves":11,"Stats":{"Battles":{"Won":1,"Lost":0},"Kills":{"Footmen":0,"Knights":0,"SiegeEngines":0,"Ships":0},"Casualties":{"Footmen":0,"Knights":0,"SiegeEngines":0,"Ships":0},"PowerTokens":{"ConsolidatePower":3,"Raids":0,"GameOfThrones":3,"Wildlings":0,"Tywin":0},"Bids":{"IronThrone":2,"Fiefdoms":0,"KingsCourt":0,"Wildlings":0,"Aeron":0}}},{"Game":302027,"House":"Tyrell","IsWinner":false,"Points":2,"BattlePenalty":0,"Strongholds":2,"Castles":0,"Cla":4,"Supplies":2,"PowerTokens":0,"MinutesPerMove":335.9,"Moves":18,"Stats":{"Battles":{"Won":0,"Lost":0},"Kills":{"Footmen":0,"Knights":0,"SiegeEngines":0,"Ships":0},"Casualties":{"Footmen":0,"Knights":0,"SiegeEngines":0,"Ships":0},"PowerTokens":{"ConsolidatePower":9,"Raids":0,"GameOfThrones":0,"Wildlings":0,"Tywin":0},"Bids":{"IronThrone":3,"Fiefdoms":2,"KingsCourt":8,"Wildlings":1,"Aeron":0}}},{"Game":301902,"House":"Greyjoy","IsWinner":true,"Points":7,"BattlePenalty":0,"Strongholds":3,"Castles":1,"Cla":5,"Supplies":4,"PowerTokens":2,"MinutesPerMove":333.7,"Moves":25,"Stats":{"Battles":{"Won":1,"Lost":0},"Kills":{"Footmen":0,"Knights":0,"SiegeEngines":0,"Ships":0},"Casualties":{"Footmen":0,"Knights":0,"SiegeEngines":0,"Ships":0},"PowerTokens":{"ConsolidatePower":4,"Raids":1,"GameOfThrones":0,"Wildlings":0,"Tywin":0},"Bids":{"IronThrone":0,"Fiefdoms":0,"KingsCourt":7,"Wildlings":0,"Aeron":0}}},{"Game":301923,"House":"Lannister","IsWinner":false,"Points":3,"BattlePenalty":0,"Strongholds":2,"Castles":1,"Cla":5,"Supplies":5,"PowerTokens":10,"MinutesPerMove":239.2,"Moves":15,"Stats":{"Battles":{"Won":0,"Lost":0},"Kills":{"Footmen":0,"Knights":0,"SiegeEngines":0,"Ships":0},"Casualties":{"Footmen":0,"Knights":0,"SiegeEngines":0,"Ships":0},"PowerTokens":{"ConsolidatePower":7,"Raids":0,"GameOfThrones":2,"Wildlings":0,"Tywin":0},"Bids":{"IronThrone":0,"Fiefdoms":0,"KingsCourt":0,"Wildlings":4,"Aeron":0}}},{"Game":301878,"House":"Martell","IsWinner":true,"Points":7,"BattlePenalty":0,"Strongholds":1,"Castles":3,"Cla":6,"Supplies":3,"PowerTokens":0,"MinutesPerMove":303.9,"Moves":16,"Stats":{"Battles":{"Won":0,"Lost":0},"Kills":{"Footmen":0,"Knights":0,"SiegeEngines":0,"Ships":0},"Casualties":{"Footmen":0,"Knights":0,"SiegeEngines":0,"Ships":0},"PowerTokens":{"ConsolidatePower":1,"Raids":0,"GameOfThrones":0,"Wildlings":0,"Tywin":0},"Bids":{"IronThrone":0,"Fiefdoms":0,"KingsCourt":5,"Wildlings":0,"Aeron":0}}}],"PenaltiesPoints":0,"PenaltiesDetails":[],"Stats":{"Battles":{"Won":3,"Lost":0},"Kills":{"Footmen":0,"Knights":0,"SiegeEngines":0,"Ships":0},"Casualties":{"Footmen":0,"Knights":0,"SiegeEngines":0,"Ships":0},"PowerTokens":{"ConsolidatePower":26,"Raids":1,"GameOfThrones":11,"Wildlings":0,"Tywin":0},"Bids":{"IronThrone":5,"Fiefdoms":2,"KingsCourt":25,"Wildlings":6,"Aeron":0}},"IsPromoted":true,"IsRelegated":false,"Position":2},{"Player":"Highlander55","TotalPoints":24,"Wins":1,"Cla":32,"Supplies":14,"PowerTokens":59,"MinutesPerMove":106.4116504854369,"Moves":103,"Houses":[{"Game":301869,"House":"Baratheon","IsWinner":false,"Points":3,"BattlePenalty":0,"Strongholds":2,"Castles":1,"Cla":4,"Supplies":2,"PowerTokens":18,"MinutesPerMove":57.6,"Moves":14,"Stats":{"Battles":{"Won":0,"Lost":0},"Kills":{"Footmen":0,"Knights":0,"SiegeEngines":0,"Ships":0},"Casualties":{"Footmen":0,"Knights":0,"SiegeEngines":0,"Ships":0},"PowerTokens":{"ConsolidatePower":5,"Raids":0,"GameOfThrones":8,"Wildlings":0,"Tywin":0},"Bids":{"IronThrone":0,"Fiefdoms":0,"KingsCourt":0,"Wildlings":0,"Aeron":0}}},{"Game":302026,"House":"Lannister","IsWinner":true,"Points":8,"BattlePenalty":0,"Strongholds":4,"Castles":1,"Cla":6,"Supplies":2,"PowerTokens":11,"MinutesPerMove":115.3,"Moves":26,"Stats":{"Battles":{"Won":3,"Lost":0},"Kills":{"Footmen":1,"Knights":3,"SiegeEngines":0,"Ships":0},"Casualties":{"Footmen":0,"Knights":0,"SiegeEngines":0,"Ships":0},"PowerTokens":{"ConsolidatePower":7,"Raids":0,"GameOfThrones":7,"Wildlings":0,"Tywin":0},"Bids":{"IronThrone":1,"Fiefdoms":0,"KingsCourt":5,"Wildlings":2,"Aeron":0}}},{"Game":301872,"House":"Stark","IsWinner":false,"Points":4,"BattlePenalty":0,"Strongholds":1,"Castles":3,"Cla":6,"Supplies":1,"PowerTokens":10,"MinutesPerMove":85.7,"Moves":11,"Stats":{"Battles":{"Won":0,"Lost":0},"Kills":{"Footmen":0,"Knights":0,"SiegeEngines":0,"Ships":0},"Casualties":{"Footmen":0,"Knights":0,"SiegeEngines":0,"Ships":0},"PowerTokens":{"ConsolidatePower":3,"Raids":0,"GameOfThrones":3,"Wildlings":0,"Tywin":0},"Bids":{"IronThrone":0,"Fiefdoms":0,"KingsCourt":0,"Wildlings":0,"Aeron":0}}},{"Game":302027,"House":"Martell","IsWinner":false,"Points":3,"BattlePenalty":0,"Strongholds":1,"Castles":2,"Cla":6,"Supplies":4,"PowerTokens":1,"MinutesPerMove":129.2,"Moves":19,"Stats":{"Battles":{"Won":0,"Lost":0},"Kills":{"Footmen":0,"Knights":0,"SiegeEngines":0,"Ships":0},"Casualties":{"Footmen":0,"Knights":0,"SiegeEngines":0,"Ships":0},"PowerTokens":{"ConsolidatePower":5,"Raids":0,"GameOfThrones":0,"Wildlings":0,"Tywin":0},"Bids":{"IronThrone":0,"Fiefdoms":4,"KingsCourt":2,"Wildlings":3,"Aeron":0}}},{"Game":301873,"House":"Greyjoy","IsWinner":false,"Points":3,"BattlePenalty":0,"Strongholds":2,"Castles":1,"Cla":5,"Supplies":3,"PowerTokens":19,"MinutesPerMove":108.3,"Moves":12,"Stats":{"Battles":{"Won":0,"Lost":0},"Kills":{"Footmen":0,"Knights":0,"SiegeEngines":0,"Ships":0},"Casualties":{"Footmen":0,"Knights":0,"SiegeEngines":0,"Ships":0},"PowerTokens":{"ConsolidatePower":8,"Raids":0,"GameOfThrones":7,"Wildlings":0,"Tywin":0},"Bids":{"IronThrone":0,"Fiefdoms":0,"KingsCourt":0,"Wildlings":1,"Aeron":0}}},{"Game":301902,"House":"Tyrell","IsWinner":false,"Points":3,"BattlePenalty":0,"Strongholds":2,"Castles":1,"Cla":5,"Supplies":2,"PowerTokens":0,"MinutesPerMove":117.1,"Moves":21,"Stats":{"Battles":{"Won":0,"Lost":0},"Kills":{"Footmen":0,"Knights":0,"SiegeEngines":0,"Ships":0},"Casualties":{"Footmen":0,"Knights":0,"SiegeEngines":0,"Ships":0},"PowerTokens":{"ConsolidatePower":6,"Raids":0,"GameOfThrones":0,"Wildlings":0,"Tywin":0},"Bids":{"IronThrone":0,"Fiefdoms":0,"KingsCourt":8,"Wildlings":3,"Aeron":0}}}],"PenaltiesPoints":0,"PenaltiesDetails":[],"Stats":{"Battles":{"Won":3,"Lost":0},"Kills":{"Footmen":1,"Knights":3,"SiegeEngines":0,"Ships":0},"Casualties":{"Footmen":0,"Knights":0,"SiegeEngines":0,"Ships":0},"PowerTokens":{"ConsolidatePower":34,"Raids":0,"GameOfThrones":25,"Wildlings":0,"Tywin":0},"Bids":{"IronThrone":1,"Fiefdoms":4,"KingsCourt":15,"Wildlings":9,"Aeron":0}},"IsPromoted":true,"IsRelegated":false,"Position":3},{"Player":"Sean_Snow","TotalPoints":21,"Wins":1,"Cla":31,"Supplies":20,"PowerTokens":46,"MinutesPerMove":129.17777777777778,"Moves":108,"Houses":[{"Game":301869,"House":"Lannister","IsWinner":false,"Points":3,"BattlePenalty":0,"Strongholds":2,"Castles":1,"Cla":6,"Supplies":6,"PowerTokens":18,"MinutesPerMove":134.7,"Moves":17,"Stats":{"Battles":{"Won":0,"Lost":0},"Kills":{"Footmen":0,"Knights":0,"SiegeEngines":0,"Ships":0},"Casualties":{"Footmen":0,"Knights":0,"SiegeEngines":0,"Ships":0},"PowerTokens":{"ConsolidatePower":5,"Raids":0,"GameOfThrones":8,"Wildlings":10,"Tywin":0},"Bids":{"IronThrone":0,"Fiefdoms":0,"KingsCourt":0,"Wildlings":10,"Aeron":0}}},{"Game":302029,"House":"Baratheon","IsWinner":false,"Points":3,"BattlePenalty":0,"Strongholds":2,"Castles":1,"Cla":5,"Supplies":2,"PowerTokens":10,"MinutesPerMove":100.7,"Moves":27,"Stats":{"Battles":{"Won":1,"Lost":2},"Kills":{"Footmen":0,"Knights":0,"SiegeEngines":0,"Ships":0},"Casualties":{"Footmen":0,"Knights":2,"SiegeEngines":0,"Ships":1},"PowerTokens":{"ConsolidatePower":5,"Raids":0,"GameOfThrones":8,"Wildlings":0,"Tywin":0},"Bids":{"IronThrone":3,"Fiefdoms":0,"KingsCourt":4,"Wildlings":0,"Aeron":0}}},{"Game":301872,"House":"Greyjoy","IsWinner":false,"Points":3,"BattlePenalty":0,"Strongholds":3,"Castles":0,"Cla":4,"Supplies":2,"PowerTokens":10,"MinutesPerMove":97.3,"Moves":12,"Stats":{"Battles":{"Won":2,"Lost":0},"Kills":{"Footmen":0,"Knights":0,"SiegeEngines":0,"Ships":1},"Casualties":{"Footmen":0,"Knights":0,"SiegeEngines":0,"Ships":0},"PowerTokens":{"ConsolidatePower":5,"Raids":0,"GameOfThrones":3,"Wildlings":0,"Tywin":0},"Bids":{"IronThrone":0,"Fiefdoms":0,"KingsCourt":0,"Wildlings":1,"Aeron":2}}},{"Game":301902,"House":"Martell","IsWinner":false,"Points":3,"BattlePenalty":0,"Strongholds":1,"Castles":2,"Cla":5,"Supplies":4,"PowerTokens":0,"MinutesPerMove":122.6,"Moves":23,"Stats":{"Battles":{"Won":0,"Lost":0},"Kills":{"Footmen":0,"Knights":0,"SiegeEngines":0,"Ships":0},"Casualties":{"Footmen":0,"Knights":0,"SiegeEngines":0,"Ships":0},"PowerTokens":{"ConsolidatePower":3,"Raids":0,"GameOfThrones":0,"Wildlings":0,"Tywin":0},"Bids":{"IronThrone":0,"Fiefdoms":4,"KingsCourt":3,"Wildlings":1,"Aeron":0}}},{"Game":301923,"House":"Stark","IsWinner":true,"Points":6,"BattlePenalty":0,"Strongholds":1,"Castles":2,"Cla":6,"Supplies":3,"PowerTokens":7,"MinutesPerMove":83.8,"Moves":13,"Stats":{"Battles":{"Won":0,"Lost":1},"Kills":{"Footmen":0,"Knights":0,"SiegeEngines":0,"Ships":0},"Casualties":{"Footmen":0,"Knights":0,"SiegeEngines":0,"Ships":0},"PowerTokens":{"ConsolidatePower":3,"Raids":0,"GameOfThrones":1,"Wildlings":0,"Tywin":0},"Bids":{"IronThrone":0,"Fiefdoms":0,"KingsCourt":0,"Wildlings":1,"Aeron":0}}},{"Game":301878,"House":"Tyrell","IsWinner":false,"Points":3,"BattlePenalty":0,"Strongholds":2,"Castles":1,"Cla":5,"Supplies":3,"PowerTokens":1,"MinutesPerMove":241.6,"Moves":16,"Stats":{"Battles":{"Won":0,"Lost":0},"Kills":{"Footmen":0,"Knights":0,"SiegeEngines":0,"Ships":0},"Casualties":{"Footmen":0,"Knights":0,"SiegeEngines":0,"Ships":0},"PowerTokens":{"ConsolidatePower":5,"Raids":1,"GameOfThrones":0,"Wildlings":0,"Tywin":0},"Bids":{"IronThrone":0,"Fiefdoms":0,"KingsCourt":9,"Wildlings":1,"Aeron":0}}}],"PenaltiesPoints":0,"PenaltiesDetails":[],"Stats":{"Battles":{"Won":3,"Lost":3},"Kills":{"Footmen":0,"Knights":0,"SiegeEngines":0,"Ships":1},"Casualties":{"Footmen":0,"Knights":2,"SiegeEngines":0,"Ships":1},"PowerTokens":{"ConsolidatePower":26,"Raids":1,"GameOfThrones":20,"Wildlings":10,"Tywin":0},"Bids":{"IronThrone":3,"Fiefdoms":4,"KingsCourt":16,"Wildlings":14,"Aeron":2}},"IsPromoted":false,"IsRelegated":false,"Position":4},{"Player":"klevushkin","TotalPoints":21,"Wins":1,"Cla":31,"Supplies":15,"PowerTokens":31,"MinutesPerMove":111.96641221374044,"Moves":131,"Houses":[{"Game":301869,"House":"Martell","IsWinner":false,"Points":3,"BattlePenalty":0,"Strongholds":1,"Castles":2,"Cla":5,"Supplies":3,"PowerTokens":14,"MinutesPerMove":55.5,"Moves":17,"Stats":{"Battles":{"Won":0,"Lost":1},"Kills":{"Footmen":0,"Knights":0,"SiegeEngines":0,"Ships":0},"Casualties":{"Footmen":0,"Knights":0,"SiegeEngines":0,"Ships":0},"PowerTokens":{"ConsolidatePower":7,"Raids":0,"GameOfThrones":8,"Wildlings":0,"Tywin":0},"Bids":{"IronThrone":0,"Fiefdoms":0,"KingsCourt":0,"Wildlings":6,"Aeron":0}}},{"Game":302029,"House":"Greyjoy","IsWinner":true,"Points":8,"BattlePenalty":0,"Strongholds":4,"Castles":1,"Cla":7,"Supplies":3,"PowerTokens":10,"MinutesPerMove":118.8,"Moves":28,"Stats":{"Battles":{"Won":4,"Lost":3},"Kills":{"Footmen":1,"Knights":4,"SiegeEngines":0,"Ships":2},"Casualties":{"Footmen":0,"Knights":0,"SiegeEngines":0,"Ships":0},"PowerTokens":{"ConsolidatePower":5,"Raids":0,"GameOfThrones":6,"Wildlings":0,"Tywin":0},"Bids":{"IronThrone":0,"Fiefdoms":1,"KingsCourt":5,"Wildlings":0,"Aeron":0}}},{"Game":302027,"House":"Lannister","IsWinner":false,"Points":2,"BattlePenalty":0,"Strongholds":2,"Castles":0,"Cla":4,"Supplies":4,"PowerTokens":2,"MinutesPerMove":166.4,"Moves":19,"Stats":{"Battles":{"Won":0,"Lost":0},"Kills":{"Footmen":0,"Knights":0,"SiegeEngines":0,"Ships":0},"Casualties":{"Footmen":0,"Knights":0,"SiegeEngines":0,"Ships":0},"PowerTokens":{"ConsolidatePower":9,"Raids":0,"GameOfThrones":0,"Wildlings":0,"Tywin":0},"Bids":{"IronThrone":2,"Fiefdoms":1,"KingsCourt":7,"Wildlings":2,"Aeron":0}}},{"Game":301902,"House":"Baratheon","IsWinner":false,"Points":3,"BattlePenalty":0,"Strongholds":2,"Castles":1,"Cla":4,"Supplies":2,"PowerTokens":0,"MinutesPerMove":125.5,"Moves":29,"Stats":{"Battles":{"Won":3,"Lost":0},"Kills":{"Footmen":0,"Knights":0,"SiegeEngines":0,"Ships":2},"Casualties":{"Footmen":0,"Knights":0,"SiegeEngines":0,"Ships":0},"PowerTokens":{"ConsolidatePower":7,"Raids":0,"GameOfThrones":0,"Wildlings":0,"Tywin":0},"Bids":{"IronThrone":3,"Fiefdoms":2,"KingsCourt":7,"Wildlings":0,"Aeron":0}}},{"Game":301874,"House":"Tyrell","IsWinner":false,"Points":2,"BattlePenalty":0,"Strongholds":2,"Castles":0,"Cla":6,"Supplies":2,"PowerTokens":5,"MinutesPerMove":107.8,"Moves":21,"Stats":{"Battles":{"Won":1,"Lost":2},"Kills":{"Footmen":0,"Knights":0,"SiegeEngines":0,"Ships":1},"Casualties":{"Footmen":0,"Knights":0,"SiegeEngines":0,"Ships":0},"PowerTokens":{"ConsolidatePower":2,"Raids":0,"GameOfThrones":4,"Wildlings":0,"Tywin":0},"Bids":{"IronThrone":2,"Fiefdoms":0,"KingsCourt":4,"Wildlings":0,"Aeron":0}}},{"Game":301878,"House":"Stark","IsWinner":false,"Points":3,"BattlePenalty":0,"Strongholds":1,"Castles":2,"Cla":5,"Supplies":1,"PowerTokens":0,"MinutesPerMove":78.4,"Moves":17,"Stats":{"Battles":{"Won":0,"Lost":0},"Kills":{"Footmen":0,"Knights":0,"SiegeEngines":0,"Ships":0},"Casualties":{"Footmen":0,"Knights":0,"SiegeEngines":0,"Ships":0},"PowerTokens":{"ConsolidatePower":1,"Raids":0,"GameOfThrones":0,"Wildlings":0,"Tywin":0},"Bids":{"IronThrone":0,"Fiefdoms":3,"KingsCourt":3,"Wildlings":0,"Aeron":0}}}],"PenaltiesPoints":0,"PenaltiesDetails":[],"Stats":{"Battles":{"Won":8,"Lost":6},"Kills":{"Footmen":1,"Knights":4,"SiegeEngines":0,"Ships":5},"Casualties":{"Footmen":0,"Knights":0,"SiegeEngines":0,"Ships":0},"PowerTokens":{"ConsolidatePower":31,"Raids":0,"GameOfThrones":18,"Wildlings":0,"Tywin":0},"Bids":{"IronThrone":7,"Fiefdoms":7,"KingsCourt":26,"Wildlings":8,"Aeron":0}},"IsPromoted":false,"IsRelegated":false,"Position":5},{"Player":"Venge","TotalPoints":20,"Wins":1,"Cla":32,"Supplies":12,"PowerTokens":56,"MinutesPerMove":112.80000000000001,"Moves":104,"Houses":[{"Game":301869,"House":"Tyrell","IsWinner":false,"Points":3,"BattlePenalty":0,"Strongholds":2,"Castles":1,"Cla":6,"Supplies":3,"PowerTokens":14,"MinutesPerMove":145.8,"Moves":12,"Stats":{"Battles":{"Won":1,"Lost":0},"Kills":{"Footmen":0,"Knights":0,"SiegeEngines":0,"Ships":0},"Casualties":{"Footmen":0,"Knights":0,"SiegeEngines":0,"Ships":0},"PowerTokens":{"ConsolidatePower":7,"Raids":0,"GameOfThrones":5,"Wildlings":0,"Tywin":0},"Bids":{"IronThrone":0,"Fiefdoms":0,"KingsCourt":0,"Wildlings":1,"Aeron":0}}},{"Game":302029,"House":"Stark","IsWinner":false,"Points":4,"BattlePenalty":0,"Strongholds":1,"Castles":3,"Cla":9,"Supplies":1,"PowerTokens":9,"MinutesPerMove":162.2,"Moves":20,"Stats":{"Battles":{"Won":1,"Lost":0},"Kills":{"Footmen":0,"Knights":0,"SiegeEngines":0,"Ships":0},"Casualties":{"Footmen":0,"Knights":0,"SiegeEngines":0,"Ships":0},"PowerTokens":{"ConsolidatePower":2,"Raids":0,"GameOfThrones":7,"Wildlings":0,"Tywin":0},"Bids":{"IronThrone":0,"Fiefdoms":0,"KingsCourt":4,"Wildlings":0,"Aeron":0}}},{"Game":302026,"House":"Greyjoy","IsWinner":false,"Points":1,"BattlePenalty":0,"Strongholds":0,"Castles":1,"Cla":3,"Supplies":2,"PowerTokens":8,"MinutesPerMove":75.8,"Moves":22,"Stats":{"Battles":{"Won":0,"Lost":4},"Kills":{"Footmen":0,"Knights":0,"SiegeEngines":0,"Ships":0},"Casualties":{"Footmen":1,"Knights":3,"SiegeEngines":0,"Ships":0},"PowerTokens":{"ConsolidatePower":3,"Raids":0,"GameOfThrones":4,"Wildlings":0,"Tywin":0},"Bids":{"IronThrone":0,"Fiefdoms":0,"KingsCourt":1,"Wildlings":1,"Aeron":0}}},{"Game":301872,"House":"Martell","IsWinner":true,"Points":7,"BattlePenalty":0,"Strongholds":1,"Castles":3,"Cla":7,"Supplies":2,"PowerTokens":6,"MinutesPerMove":159.9,"Moves":13,"Stats":{"Battles":{"Won":0,"Lost":1},"Kills":{"Footmen":0,"Knights":0,"SiegeEngines":0,"Ships":0},"Casualties":{"Footmen":0,"Knights":0,"SiegeEngines":0,"Ships":0},"PowerTokens":{"ConsolidatePower":1,"Raids":0,"GameOfThrones":2,"Wildlings":0,"Tywin":0},"Bids":{"IronThrone":0,"Fiefdoms":0,"KingsCourt":0,"Wildlings":0,"Aeron":0}}},{"Game":301873,"House":"Baratheon","IsWinner":false,"Points":3,"BattlePenalty":0,"Strongholds":2,"Castles":1,"Cla":5,"Supplies":2,"PowerTokens":14,"MinutesPerMove":101.3,"Moves":15,"Stats":{"Battles":{"Won":0,"Lost":0},"Kills":{"Footmen":0,"Knights":0,"SiegeEngines":0,"Ships":0},"Casualties":{"Footmen":0,"Knights":0,"SiegeEngines":0,"Ships":0},"PowerTokens":{"ConsolidatePower":6,"Raids":0,"GameOfThrones":9,"Wildlings":0,"Tywin":0},"Bids":{"IronThrone":0,"Fiefdoms":0,"KingsCourt":0,"Wildlings":5,"Aeron":0}}},{"Game":301874,"House":"Lannister","IsWinner":false,"Points":2,"BattlePenalty":0,"Strongholds":1,"Castles":1,"Cla":2,"Supplies":2,"PowerTokens":5,"MinutesPerMove":66.9,"Moves":22,"Stats":{"Battles":{"Won":1,"Lost":4},"Kills":{"Footmen":0,"Knights":0,"SiegeEngines":0,"Ships":1},"Casualties":{"Footmen":0,"Knights":1,"SiegeEngines":0,"Ships":0},"PowerTokens":{"ConsolidatePower":3,"Raids":0,"GameOfThrones":2,"Wildlings":0,"Tywin":0},"Bids":{"IronThrone":0,"Fiefdoms":3,"KingsCourt":1,"Wildlings":1,"Aeron":0}}}],"PenaltiesPoints":0,"PenaltiesDetails":[],"Stats":{"Battles":{"Won":3,"Lost":9},"Kills":{"Footmen":0,"Knights":0,"SiegeEngines":0,"Ships":1},"Casualties":{"Footmen":1,"Knights":4,"SiegeEngines":0,"Ships":0},"PowerTokens":{"ConsolidatePower":22,"Raids":0,"GameOfThrones":29,"Wildlings":0,"Tywin":0},"Bids":{"IronThrone":0,"Fiefdoms":3,"KingsCourt":6,"Wildlings":8,"Aeron":0}},"IsPromoted":false,"IsRelegated":false,"Position":6},{"Player":"RodrigoLannister","TotalPoints":20,"Wins":1,"Cla":25,"Supplies":15,"PowerTokens":45,"MinutesPerMove":593.7922222222222,"Moves":90,"Houses":[{"Game":301869,"House":"Stark","IsWinner":true,"Points":7,"BattlePenalty":0,"Strongholds":1,"Castles":3,"Cla":5,"Supplies":2,"PowerTokens":9,"MinutesPerMove":517.2,"Moves":17,"Stats":{"Battles":{"Won":1,"Lost":1},"Kills":{"Footmen":0,"Knights":1,"SiegeEngines":0,"Ships":0},"Casualties":{"Footmen":0,"Knights":0,"SiegeEngines":0,"Ships":0},"PowerTokens":{"ConsolidatePower":2,"Raids":0,"GameOfThrones":6,"Wildlings":0,"Tywin":0},"Bids":{"IronThrone":0,"Fiefdoms":0,"KingsCourt":0,"Wildlings":2,"Aeron":0}}},{"Game":301872,"House":"Lannister","IsWinner":false,"Points":2,"BattlePenalty":0,"Strongholds":1,"Castles":1,"Cla":3,"Supplies":2,"PowerTokens":7,"MinutesPerMove":667.6,"Moves":14,"Stats":{"Battles":{"Won":0,"Lost":2},"Kills":{"Footmen":0,"Knights":0,"SiegeEngines":0,"Ships":0},"Casualties":{"Footmen":0,"Knights":0,"SiegeEngines":0,"Ships":1},"PowerTokens":{"ConsolidatePower":3,"Raids":0,"GameOfThrones":2,"Wildlings":0,"Tywin":0},"Bids":{"IronThrone":3,"Fiefdoms":0,"KingsCourt":0,"Wildlings":0,"Aeron":0}}},{"Game":301873,"House":"Tyrell","IsWinner":false,"Points":2,"BattlePenalty":0,"Strongholds":2,"Castles":0,"Cla":5,"Supplies":3,"PowerTokens":15,"MinutesPerMove":653.9,"Moves":11,"Stats":{"Battles":{"Won":0,"Lost":0},"Kills":{"Footmen":0,"Knights":0,"SiegeEngines":0,"Ships":0},"Casualties":{"Footmen":0,"Knights":0,"SiegeEngines":0,"Ships":0},"PowerTokens":{"ConsolidatePower":8,"Raids":0,"GameOfThrones":5,"Wildlings":0,"Tywin":0},"Bids":{"IronThrone":0,"Fiefdoms":0,"KingsCourt":0,"Wildlings":2,"Aeron":0}}},{"Game":301874,"House":"Baratheon","IsWinner":false,"Points":3,"BattlePenalty":0,"Strongholds":2,"Castles":1,"Cla":5,"Supplies":3,"PowerTokens":7,"MinutesPerMove":615.8,"Moves":15,"Stats":{"Battles":{"Won":0,"Lost":0},"Kills":{"Footmen":0,"Knights":0,"SiegeEngines":0,"Ships":0},"Casualties":{"Footmen":0,"Knights":0,"SiegeEngines":0,"Ships":0},"PowerTokens":{"ConsolidatePower":2,"Raids":0,"GameOfThrones":5,"Wildlings":0,"Tywin":0},"Bids":{"IronThrone":1,"Fiefdoms":0,"KingsCourt":2,"Wildlings":2,"Aeron":0}}},{"Game":301923,"House":"Martell","IsWinner":false,"Points":3,"BattlePenalty":0,"Strongholds":2,"Castles":1,"Cla":3,"Supplies":2,"PowerTokens":6,"MinutesPerMove":557.4,"Moves":17,"Stats":{"Battles":{"Won":2,"Lost":1},"Kills":{"Footmen":0,"Knights":0,"SiegeEngines":0,"Ships":1},"Casualties":{"Footmen":1,"Knights":0,"SiegeEngines":0,"Ships":0},"PowerTokens":{"ConsolidatePower":2,"Raids":0,"GameOfThrones":1,"Wildlings":0,"Tywin":0},"Bids":{"IronThrone":0,"Fiefdoms":0,"KingsCourt":0,"Wildlings":2,"Aeron":0}}},{"Game":301878,"House":"Greyjoy","IsWinner":false,"Points":3,"BattlePenalty":0,"Strongholds":2,"Castles":1,"Cla":4,"Supplies":3,"PowerTokens":1,"MinutesPerMove":587.3,"Moves":16,"Stats":{"Battles":{"Won":0,"Lost":0},"Kills":{"Footmen":0,"Knights":0,"SiegeEngines":0,"Ships":0},"Casualties":{"Footmen":0,"Knights":0,"SiegeEngines":0,"Ships":0},"PowerTokens":{"ConsolidatePower":3,"Raids":0,"GameOfThrones":0,"Wildlings":0,"Tywin":0},"Bids":{"IronThrone":0,"Fiefdoms":2,"KingsCourt":4,"Wildlings":1,"Aeron":0}}}],"PenaltiesPoints":0,"PenaltiesDetails":[],"Stats":{"Battles":{"Won":3,"Lost":4},"Kills":{"Footmen":0,"Knights":1,"SiegeEngines":0,"Ships":1},"Casualties":{"Footmen":1,"Knights":0,"SiegeEngines":0,"Ships":1},"PowerTokens":{"ConsolidatePower":20,"Raids":0,"GameOfThrones":19,"Wildlings":0,"Tywin":0},"Bids":{"IronThrone":4,"Fiefdoms":2,"KingsCourt":6,"Wildlings":9,"Aeron":0}},"IsPromoted":false,"IsRelegated":false,"Position":7},{"Player":"Figueira","TotalPoints":19,"Wins":0,"Cla":35,"Supplies":17,"PowerTokens":29,"MinutesPerMove":159.5039603960396,"Moves":101,"Houses":[{"Game":302029,"House":"Martell","IsWinner":false,"Points":4,"BattlePenalty":0,"Strongholds":1,"Castles":3,"Cla":7,"Supplies":3,"PowerTokens":5,"MinutesPerMove":140,"Moves":18,"Stats":{"Battles":{"Won":2,"Lost":1},"Kills":{"Footmen":0,"Knights":0,"SiegeEngines":0,"Ships":1},"Casualties":{"Footmen":0,"Knights":0,"SiegeEngines":0,"Ships":0},"PowerTokens":{"ConsolidatePower":3,"Raids":0,"GameOfThrones":3,"Wildlings":0,"Tywin":0},"Bids":{"IronThrone":0,"Fiefdoms":4,"KingsCourt":0,"Wildlings":0,"Aeron":0}}},{"Game":302026,"House":"Baratheon","IsWinner":false,"Points":3,"BattlePenalty":0,"Strongholds":1,"Castles":2,"Cla":6,"Supplies":2,"PowerTokens":12,"MinutesPerMove":124.8,"Moves":19,"Stats":{"Battles":{"Won":1,"Lost":1},"Kills":{"Footmen":0,"Knights":0,"SiegeEngines":0,"Ships":0},"Casualties":{"Footmen":0,"Knights":0,"SiegeEngines":0,"Ships":0},"PowerTokens":{"ConsolidatePower":5,"Raids":0,"GameOfThrones":9,"Wildlings":0,"Tywin":0},"Bids":{"IronThrone":0,"Fiefdoms":1,"KingsCourt":4,"Wildlings":0,"Aeron":0}}},{"Game":301872,"House":"Tyrell","IsWinner":false,"Points":3,"BattlePenalty":0,"Strongholds":2,"Castles":1,"Cla":7,"Supplies":2,"PowerTokens":10,"MinutesPerMove":116,"Moves":9,"Stats":{"Battles":{"Won":0,"Lost":0},"Kills":{"Footmen":0,"Knights":0,"SiegeEngines":0,"Ships":0},"Casualties":{"Footmen":0,"Knights":0,"SiegeEngines":0,"Ships":0},"PowerTokens":{"ConsolidatePower":6,"Raids":0,"GameOfThrones":2,"Wildlings":0,"Tywin":0},"Bids":{"IronThrone":0,"Fiefdoms":0,"KingsCourt":0,"Wildlings":2,"Aeron":0}}},{"Game":302027,"House":"Greyjoy","IsWinner":false,"Points":3,"BattlePenalty":0,"Strongholds":2,"Castles":1,"Cla":5,"Supplies":4,"PowerTokens":0,"MinutesPerMove":179.9,"Moves":24,"Stats":{"Battles":{"Won":2,"Lost":1},"Kills":{"Footmen":0,"Knights":0,"SiegeEngines":0,"Ships":0},"Casualties":{"Footmen":1,"Knights":0,"SiegeEngines":0,"Ships":0},"PowerTokens":{"ConsolidatePower":7,"Raids":0,"GameOfThrones":0,"Wildlings":0,"Tywin":0},"Bids":{"IronThrone":2,"Fiefdoms":5,"KingsCourt":0,"Wildlings":2,"Aeron":2}}},{"Game":301902,"House":"Lannister","IsWinner":false,"Points":3,"BattlePenalty":0,"Strongholds":2,"Castles":1,"Cla":5,"Supplies":5,"PowerTokens":0,"MinutesPerMove":194.6,"Moves":16,"Stats":{"Battles":{"Won":0,"Lost":0},"Kills":{"Footmen":0,"Knights":0,"SiegeEngines":0,"Ships":0},"Casualties":{"Footmen":0,"Knights":0,"SiegeEngines":0,"Ships":0},"PowerTokens":{"ConsolidatePower":5,"Raids":0,"GameOfThrones":0,"Wildlings":0,"Tywin":0},"Bids":{"IronThrone":1,"Fiefdoms":1,"KingsCourt":7,"Wildlings":1,"Aeron":0}}},{"Game":301874,"House":"Stark","IsWinner":false,"Points":3,"BattlePenalty":0,"Strongholds":1,"Castles":2,"Cla":5,"Supplies":1,"PowerTokens":2,"MinutesPerMove":182.9,"Moves":15,"Stats":{"Battles":{"Won":0,"Lost":0},"Kills":{"Footmen":0,"Knights":0,"SiegeEngines":0,"Ships":0},"Casualties":{"Footmen":0,"Knights":0,"SiegeEngines":0,"Ships":0},"PowerTokens":{"ConsolidatePower":1,"Raids":0,"GameOfThrones":3,"Wildlings":0,"Tywin":0},"Bids":{"IronThrone":0,"Fiefdoms":0,"KingsCourt":6,"Wildlings":1,"Aeron":0}}}],"PenaltiesPoints":0,"PenaltiesDetails":[],"Stats":{"Battles":{"Won":5,"Lost":3},"Kills":{"Footmen":0,"Knights":0,"SiegeEngines":0,"Ships":1},"Casualties":{"Footmen":1,"Knights":0,"SiegeEngines":0,"Ships":0},"PowerTokens":{"ConsolidatePower":27,"Raids":0,"GameOfThrones":17,"Wildlings":0,"Tywin":0},"Bids":{"IronThrone":3,"Fiefdoms":11,"KingsCourt":17,"Wildlings":6,"Aeron":2}},"IsPromoted":false,"IsRelegated":true,"Position":8},{"Player":"Ser Joseph","TotalPoints":18,"Wins":1,"Cla":26,"Supplies":10,"PowerTokens":52,"MinutesPerMove":263.5580645161291,"Moves":124,"Houses":[{"Game":302029,"House":"Lannister","IsWinner":false,"Points":0,"BattlePenalty":0,"Strongholds":0,"Castles":0,"Cla":0,"Supplies":2,"PowerTokens":11,"MinutesPerMove":225.3,"Moves":33,"Stats":{"Battles":{"Won":1,"Lost":8},"Kills":{"Footmen":0,"Knights":0,"SiegeEngines":0,"Ships":0},"Casualties":{"Footmen":3,"Knights":5,"SiegeEngines":1,"Ships":2},"PowerTokens":{"ConsolidatePower":4,"Raids":0,"GameOfThrones":6,"Wildlings":0,"Tywin":2},"Bids":{"IronThrone":0,"Fiefdoms":1,"KingsCourt":5,"Wildlings":0,"Aeron":0}}},{"Game":302026,"House":"Tyrell","IsWinner":false,"Points":4,"BattlePenalty":0,"Strongholds":3,"Castles":1,"Cla":8,"Supplies":2,"PowerTokens":10,"MinutesPerMove":250.4,"Moves":20,"Stats":{"Battles":{"Won":1,"Lost":1},"Kills":{"Footmen":0,"Knights":0,"SiegeEngines":0,"Ships":0},"Casualties":{"Footmen":0,"Knights":0,"SiegeEngines":0,"Ships":0},"PowerTokens":{"ConsolidatePower":7,"Raids":0,"GameOfThrones":5,"Wildlings":0,"Tywin":0},"Bids":{"IronThrone":0,"Fiefdoms":0,"KingsCourt":5,"Wildlings":1,"Aeron":0}}},{"Game":301873,"House":"Martell","IsWinner":true,"Points":7,"BattlePenalty":0,"Strongholds":1,"Castles":3,"Cla":6,"Supplies":2,"PowerTokens":13,"MinutesPerMove":309.9,"Moves":13,"Stats":{"Battles":{"Won":0,"Lost":0},"Kills":{"Footmen":0,"Knights":0,"SiegeEngines":0,"Ships":0},"Casualties":{"Footmen":0,"Knights":0,"SiegeEngines":0,"Ships":0},"PowerTokens":{"ConsolidatePower":5,"Raids":0,"GameOfThrones":6,"Wildlings":0,"Tywin":0},"Bids":{"IronThrone":0,"Fiefdoms":0,"KingsCourt":0,"Wildlings":1,"Aeron":0}}},{"Game":301902,"House":"Stark","IsWinner":false,"Points":1,"BattlePenalty":0,"Strongholds":0,"Castles":1,"Cla":3,"Supplies":0,"PowerTokens":0,"MinutesPerMove":211.5,"Moves":25,"Stats":{"Battles":{"Won":0,"Lost":4},"Kills":{"Footmen":0,"Knights":0,"SiegeEngines":0,"Ships":0},"Casualties":{"Footmen":0,"Knights":0,"SiegeEngines":0,"Ships":2},"PowerTokens":{"ConsolidatePower":2,"Raids":0,"GameOfThrones":0,"Wildlings":0,"Tywin":0},"Bids":{"IronThrone":0,"Fiefdoms":4,"KingsCourt":2,"Wildlings":0,"Aeron":0}}},{"Game":301874,"House":"Greyjoy","IsWinner":false,"Points":3,"BattlePenalty":0,"Strongholds":2,"Castles":1,"Cla":5,"Supplies":2,"PowerTokens":3,"MinutesPerMove":382.7,"Moves":23,"Stats":{"Battles":{"Won":4,"Lost":2},"Kills":{"Footmen":0,"Knights":1,"SiegeEngines":0,"Ships":0},"Casualties":{"Footmen":0,"Knights":0,"SiegeEngines":0,"Ships":2},"PowerTokens":{"ConsolidatePower":2,"Raids":0,"GameOfThrones":4,"Wildlings":0,"Tywin":0},"Bids":{"IronThrone":0,"Fiefdoms":0,"KingsCourt":7,"Wildlings":1,"Aeron":0}}},{"Game":301923,"House":"Baratheon","IsWinner":false,"Points":3,"BattlePenalty":0,"Strongholds":2,"Castles":1,"Cla":4,"Supplies":2,"PowerTokens":15,"MinutesPerMove":212,"Moves":10,"Stats":{"Battles":{"Won":0,"Lost":0},"Kills":{"Footmen":0,"Knights":0,"SiegeEngines":0,"Ships":0},"Casualties":{"Footmen":0,"Knights":0,"SiegeEngines":0,"Ships":0},"PowerTokens":{"ConsolidatePower":10,"Raids":0,"GameOfThrones":3,"Wildlings":0,"Tywin":0},"Bids":{"IronThrone":0,"Fiefdoms":0,"KingsCourt":0,"Wildlings":3,"Aeron":0}}}],"PenaltiesPoints":0,"PenaltiesDetails":[],"Stats":{"Battles":{"Won":6,"Lost":15},"Kills":{"Footmen":0,"Knights":1,"SiegeEngines":0,"Ships":0},"Casualties":{"Footmen":3,"Knights":5,"SiegeEngines":1,"Ships":6},"PowerTokens":{"ConsolidatePower":30,"Raids":0,"GameOfThrones":24,"Wildlings":0,"Tywin":2},"Bids":{"IronThrone":0,"Fiefdoms":5,"KingsCourt":19,"Wildlings":6,"Aeron":0}},"IsPromoted":false,"IsRelegated":true,"Position":9},{"Player":"squallwst","TotalPoints":16,"Wins":0,"Cla":28,"Supplies":15,"PowerTokens":55,"MinutesPerMove":366.22142857142853,"Moves":98,"Houses":[{"Game":301869,"House":"Greyjoy","IsWinner":false,"Points":3,"BattlePenalty":0,"Strongholds":2,"Castles":1,"Cla":4,"Supplies":3,"PowerTokens":16,"MinutesPerMove":450.5,"Moves":17,"Stats":{"Battles":{"Won":1,"Lost":1},"Kills":{"Footmen":0,"Knights":0,"SiegeEngines":0,"Ships":0},"Casualties":{"Footmen":0,"Knights":1,"SiegeEngines":0,"Ships":0},"PowerTokens":{"ConsolidatePower":8,"Raids":0,"GameOfThrones":6,"Wildlings":0,"Tywin":0},"Bids":{"IronThrone":0,"Fiefdoms":0,"KingsCourt":0,"Wildlings":3,"Aeron":0}}},{"Game":302026,"House":"Martell","IsWinner":false,"Points":3,"BattlePenalty":0,"Strongholds":1,"Castles":2,"Cla":5,"Supplies":2,"PowerTokens":11,"MinutesPerMove":268.9,"Moves":14,"Stats":{"Battles":{"Won":0,"Lost":0},"Kills":{"Footmen":0,"Knights":0,"SiegeEngines":0,"Ships":0},"Casualties":{"Footmen":0,"Knights":0,"SiegeEngines":0,"Ships":0},"PowerTokens":{"ConsolidatePower":5,"Raids":0,"GameOfThrones":5,"Wildlings":0,"Tywin":0},"Bids":{"IronThrone":0,"Fiefdoms":2,"KingsCourt":0,"Wildlings":1,"Aeron":0}}},{"Game":302027,"House":"Stark","IsWinner":false,"Points":3,"BattlePenalty":0,"Strongholds":1,"Castles":2,"Cla":5,"Supplies":3,"PowerTokens":0,"MinutesPerMove":328.1,"Moves":25,"Stats":{"Battles":{"Won":1,"Lost":3},"Kills":{"Footmen":1,"Knights":0,"SiegeEngines":0,"Ships":0},"Casualties":{"Footmen":0,"Knights":0,"SiegeEngines":0,"Ships":0},"PowerTokens":{"ConsolidatePower":4,"Raids":0,"GameOfThrones":0,"Wildlings":0,"Tywin":0},"Bids":{"IronThrone":0,"Fiefdoms":1,"KingsCourt":6,"Wildlings":1,"Aeron":0}}},{"Game":301873,"House":"Lannister","IsWinner":false,"Points":3,"BattlePenalty":0,"Strongholds":2,"Castles":1,"Cla":6,"Supplies":2,"PowerTokens":20,"MinutesPerMove":430.2,"Moves":13,"Stats":{"Battles":{"Won":0,"Lost":0},"Kills":{"Footmen":0,"Knights":0,"SiegeEngines":0,"Ships":0},"Casualties":{"Footmen":0,"Knights":0,"SiegeEngines":0,"Ships":0},"PowerTokens":{"ConsolidatePower":5,"Raids":0,"GameOfThrones":10,"Wildlings":0,"Tywin":0},"Bids":{"IronThrone":0,"Fiefdoms":0,"KingsCourt":0,"Wildlings":0,"Aeron":0}}},{"Game":301923,"House":"Tyrell","IsWinner":false,"Points":1,"BattlePenalty":0,"Strongholds":1,"Castles":0,"Cla":4,"Supplies":3,"PowerTokens":7,"MinutesPerMove":366.1,"Moves":15,"Stats":{"Battles":{"Won":1,"Lost":2},"Kills":{"Footmen":1,"Knights":0,"SiegeEngines":0,"Ships":0},"Casualties":{"Footmen":0,"Knights":0,"SiegeEngines":0,"Ships":1},"PowerTokens":{"ConsolidatePower":6,"Raids":0,"GameOfThrones":2,"Wildlings":0,"Tywin":0},"Bids":{"IronThrone":0,"Fiefdoms":0,"KingsCourt":0,"Wildlings":5,"Aeron":0}}},{"Game":301878,"House":"Baratheon","IsWinner":false,"Points":3,"BattlePenalty":0,"Strongholds":2,"Castles":1,"Cla":4,"Supplies":2,"PowerTokens":1,"MinutesPerMove":370,"Moves":14,"Stats":{"Battles":{"Won":0,"Lost":0},"Kills":{"Footmen":0,"Knights":0,"SiegeEngines":0,"Ships":0},"Casualties":{"Footmen":0,"Knights":0,"SiegeEngines":0,"Ships":0},"PowerTokens":{"ConsolidatePower":5,"Raids":1,"GameOfThrones":0,"Wildlings":0,"Tywin":0},"Bids":{"IronThrone":1,"Fiefdoms":0,"KingsCourt":9,"Wildlings":0,"Aeron":0}}}],"PenaltiesPoints":0,"PenaltiesDetails":[],"Stats":{"Battles":{"Won":3,"Lost":6},"Kills":{"Footmen":2,"Knights":0,"SiegeEngines":0,"Ships":0},"Casualties":{"Footmen":0,"Knights":1,"SiegeEngines":0,"Ships":1},"PowerTokens":{"ConsolidatePower":33,"Raids":1,"GameOfThrones":23,"Wildlings":0,"Tywin":0},"Bids":{"IronThrone":1,"Fiefdoms":3,"KingsCourt":15,"Wildlings":10,"Aeron":0}},"IsPromoted":false,"IsRelegated":true,"Position":10}],"GeneratedTime":"2024-01-27T05:52:55.2789716+00:00","IsFinished":false,"IsCreatedManually":false}